codeforces/__init__.py
codeforces/api.py
codeforces/cf_run.py
codeforces/error.py
codeforces/problem.py
codeforces/submission.py
python_codeforces-0.2.7.dist-info/LICENSE
python_codeforces-0.2.7.dist-info/METADATA
python_codeforces-0.2.7.dist-info/WHEEL
python_codeforces-0.2.7.dist-info/entry_points.txt
python_codeforces-0.2.7.dist-info/top_level.txt
python_codeforces-0.2.7.dist-info/RECORD
