Metadata-Version: 2.1
Name: python-codeforces
Version: 0.2.7
Summary: Codeforces API wrapper for python
Home-page: https://github.com/Mukundan314/python-codeforces
Author: Mukundan
Author-email: mukundan314@gmail.com
License: MIT
Project-URL: Bug Tracker, https://github.com/Mukundan314/python-codeforces/issues/
Project-URL: Documentation, https://python-codeforces.readthedocs.io/en/stable/
Project-URL: Source, https://github.com/Mukundan314/python-codeforces
Keywords: codeforces
Platform: UNKNOWN
Classifier: Development Status :: 5 - Production/Stable
Classifier: Intended Audience :: Developers
Classifier: License :: OSI Approved :: MIT License
Classifier: Programming Language :: Python :: 3
Classifier: Programming Language :: Python :: 3.6
Classifier: Programming Language :: Python :: 3.7
Requires-Python: >=3.6,<4
